raglens/__init__.py
raglens/embeddings.py
raglens/explainer.py
raglens/retrieval.py
raglens/visualization.py
raglens-0.1.4.dist-info/licenses/LICENSE
raglens-0.1.4.dist-info/METADATA
raglens-0.1.4.dist-info/WHEEL
raglens-0.1.4.dist-info/top_level.txt
raglens-0.1.4.dist-info/RECORD
