Metadata-Version: 2.4
Name: raglens
Version: 0.1.4
Summary: Embedding diagnostics toolkit for RAG systems
Project-URL: Homepage, https://github.com/gegedenice/raglens
Requires-Python: >=3.11
License-File: LICENSE
Requires-Dist: ipykernel>=6.30.0
Requires-Dist: matplotlib>=3.10.3
Requires-Dist: openai>=1.98.0
Requires-Dist: scikit-learn>=1.7.1
Requires-Dist: streamlit>=1.47.1
Requires-Dist: torch>=2.7.1
Requires-Dist: transformers>=4.54.1
Requires-Dist: umap-learn>=0.5.9.post2
Dynamic: license-file
